{
  "source": "arwu",
  "country": null,
  "coverage": "worldwide",
  "ranking_year": 2025,
  "retrieval_method": "public-json",
  "data_license": "Copyright ShanghaiRanking Consultancy",
  "data_attribution": "Academic Ranking of World Universities and Global Ranking of Academic Subjects, ShanghaiRanking Consultancy, shanghairanking.com",
  "retrieved_at": "2026-07-19T13:19:25+00:00",
  "records": 20650,
  "records_by_scope": {
    "aerospace-engineering": 100,
    "agricultural-sciences": 500,
    "artificial-intelligence": 400,
    "atmospheric-science": 400,
    "automation-control": 200,
    "biological-sciences": 500,
    "biomedical-engineering": 300,
    "biotechnology": 400,
    "business-administration": 400,
    "chemical-engineering": 500,
    "chemistry": 500,
    "civil-engineering": 400,
    "clinical-medicine": 500,
    "communication": 200,
    "computer-science-engineering": 500,
    "dentistry-oral-sciences": 300,
    "earth-sciences": 500,
    "ecology": 400,
    "economics": 500,
    "education": 500,
    "electrical-electronic-engineering": 500,
    "energy-science-engineering": 400,
    "environmental-science-engineering": 500,
    "finance": 200,
    "food-science-technology": 400,
    "geography": 200,
    "hospitality-tourism-management": 100,
    "human-biological-sciences": 500,
    "instruments-science-technology": 400,
    "law": 200,
    "library-information-science": 100,
    "management": 500,
    "marine-ocean-engineering": 100,
    "materials-science-engineering": 500,
    "mathematics": 500,
    "mechanical-engineering": 400,
    "medical-technology": 300,
    "metallurgical-engineering": 300,
    "mining-mineral-engineering": 100,
    "nanoscience-nanotechnology": 400,
    "nursing": 300,
    "oceanography": 200,
    "overall": 1000,
    "pharmacy-pharmaceutical-sciences": 500,
    "physics": 500,
    "political-sciences": 300,
    "psychology": 500,
    "public-administration": 100,
    "public-health": 500,
    "remote-sensing": 200,
    "robotic-science-engineering": 100,
    "sociology": 300,
    "statistics": 300,
    "telecommunication-engineering": 400,
    "textile-science-engineering": 50,
    "transportation-science-technology": 200,
    "veterinary-sciences": 300,
    "water-resources": 300
  },
  "failures": []
}
